{"吉林": "4", "欧亚": "4", "打扰": "4", "置业": "3", "万元": "3", "你好": "3", "单位": "3", "多余": "3", "票据": "3", "对外": "3", "国地税": "3", "增值税": "3", "抵扣": "3", "通用机": "3", "承诺": "3", "真票": "3", "可验证": "3", "付款": "3", "电话": "3", "赵小姐": "3", "谅解": "3", "增资": "2", "亿元": "2", "公司": "1", "全资": "1", "子公司": "1", "有限公司": "1", "注册资本": "1", "增加": "1", "经营范围": "1", "房地产": "1", "开发": "1", "百货": "1", "零售": "1", "业务": "1", "在建": "1", "城市": "1", "商业": "1", "综合体": "1", "项目": "1", "营业": "1", "收入": "1", "净利润": "1", "提供": "1", "酒店": "1", "公寓": "1", "上门服务": "1", "学生": "1", "白领": "1", "少妇": "1"}